{
    "status": "OK",
    "bill": {
        "bill_id": 1543502,
        "change_hash": "f93a20939a1c3bd06bb76535b17da66e",
        "session_id": 1959,
        "session": {
            "session_id": 1959,
            "state_id": 29,
            "year_start": 2022,
            "year_end": 2022,
            "prefile": 0,
            "sine_die": 0,
            "prior": 0,
            "special": 0,
            "session_tag": "Regular Session",
            "session_title": "2022 Regular Session",
            "session_name": "2022 Regular Session"
        },
        "url": "https://legiscan.com/NH/bill/HB1337/2022",
        "state_link": "https://gencourt.state.nh.us/bill_status/legacy/bs2016/bill_status.aspx?lsr=2295&sy=2022&sortoption=&txtsessionyear=2022&txtbillnumber=HB1337",
        "completed": 0,
        "status": 2,
        "status_date": "2022-03-22",
        "progress": [
            {
                "date": "2021-11-20",
                "event": 1
            },
            {
                "date": "2021-11-20",
                "event": 9
            },
            {
                "date": "2022-03-10",
                "event": 10
            },
            {
                "date": "2022-03-10",
                "event": 11
            },
            {
                "date": "2022-03-22",
                "event": 2
            },
            {
                "date": "2022-03-22",
                "event": 9
            },
            {
                "date": "2022-04-06",
                "event": 11
            }
        ],
        "state": "NH",
        "state_id": 29,
        "bill_number": "HB1337",
        "bill_type": "B",
        "bill_type_id": "1",
        "body": "H",
        "body_id": 67,
        "current_body": "S",
        "current_body_id": 68,
        "title": "Relative to the duration of unemployment benefits.",
        "description": "Relative to the duration of unemployment benefits.",
        "pending_committee_id": 0,
        "committee": [],
        "referrals": [
            {
                "date": "2021-11-20",
                "committee_id": 1251,
                "chamber": "H",
                "chamber_id": 67,
                "name": "Labor, Industrial and Rehabilitative Services"
            },
            {
                "date": "2022-03-22",
                "committee_id": 1270,
                "chamber": "S",
                "chamber_id": 68,
                "name": "Executive Departments and Administration"
            }
        ],
        "history": [
            {
                "date": "2021-11-20",
                "action": "Introduced 01/05/2022 and referred to Labor, Industrial and Rehabilitative Services",
                "chamber": "H",
                "chamber_id": 67,
                "importance": 1
            },
            {
                "date": "2022-02-03",
                "action": "Public Hearing: 02/03/2022 1:00 p.m. Legislative Office Building305-307",
                "chamber": "H",
                "chamber_id": 67,
                "importance": 0
            },
            {
                "date": "2022-02-28",
                "action": "Executive Session: 03/09/2022 10:00 am Legislative Office Building 305-307",
                "chamber": "H",
                "chamber_id": 67,
                "importance": 0
            },
            {
                "date": "2022-03-09",
                "action": "Executive Session: 03/09/2022 10:00 a.m. Legislative Office Building305-307",
                "chamber": "H",
                "chamber_id": 67,
                "importance": 0
            },
            {
                "date": "2022-03-10",
                "action": "Majority Committee Report: Ought to Pass with Amendment # 2022-0732h (Vote 11-10; Regular Calendar)",
                "chamber": "H",
                "chamber_id": 67,
                "importance": 1
            },
            {
                "date": "2022-03-10",
                "action": "Minority Committee Report: Inexpedient to Legislate",
                "chamber": "H",
                "chamber_id": 67,
                "importance": 1
            },
            {
                "date": "2022-03-17",
                "action": "Amendment # 2022-0732h: Amendment Adopted Voice Vote 03/17/2022 House Journal  8",
                "chamber": "H",
                "chamber_id": 67,
                "importance": 0
            },
            {
                "date": "2022-03-17",
                "action": "Ought to Pass with Amendment 2022-0732h: Motion Adopted Regular Calendar 179-153 03/17/2022 House Journal  8",
                "chamber": "H",
                "chamber_id": 67,
                "importance": 0
            },
            {
                "date": "2022-03-22",
                "action": "Introduced 03/17/2022 and Referred to Executive Departments and Administration; Senate Journal 6",
                "chamber": "S",
                "chamber_id": 68,
                "importance": 1
            },
            {
                "date": "2022-03-31",
                "action": "Hearing: 04/06/2022, Room 103, State House, 10:00 am; Senate Calendar  14",
                "chamber": "S",
                "chamber_id": 68,
                "importance": 0
            },
            {
                "date": "2022-04-06",
                "action": "Committee Report: Inexpedient to Legislate; Vote 5-0; Consent Calendar; 04/14/2022; Senate Calendar  15",
                "chamber": "S",
                "chamber_id": 68,
                "importance": 1
            },
            {
                "date": "2022-04-14",
                "action": "Inexpedient to Legislate, Motion Adopted, Voice Vote === BILL KILLED ===; 04/14/2022; Senate Journal 8",
                "chamber": "S",
                "chamber_id": 68,
                "importance": 0
            }
        ],
        "sponsors": [
            {
                "people_id": 17493,
                "person_hash": "upw2sr1e",
                "party_id": "2",
                "state_id": 29,
                "party": "R",
                "role_id": 1,
                "role": "Rep",
                "name": "Leonard Turcotte",
                "first_name": "Leonard",
                "middle_name": "",
                "last_name": "Turcotte",
                "suffix": "",
                "nickname": "Len",
                "district": "HD-04-STR",
                "ftm_eid": 13703851,
                "votesmart_id": 141973,
                "opensecrets_id": "",
                "knowwho_pid": 436666,
                "ballotpedia": "Len_Turcotte",
                "sponsor_type_id": 1,
                "sponsor_order": 1,
                "committee_sponsor": 0,
                "committee_id": 0,
                "state_federal": 0
            },
            {
                "people_id": 17302,
                "person_hash": "xh0ul6ms",
                "party_id": "2",
                "state_id": 29,
                "party": "R",
                "role_id": 1,
                "role": "Rep",
                "name": "Fred Doucette",
                "first_name": "Fred",
                "middle_name": "",
                "last_name": "Doucette",
                "suffix": "",
                "nickname": "",
                "district": "HD-08-ROC",
                "ftm_eid": 25005600,
                "votesmart_id": 154566,
                "opensecrets_id": "",
                "knowwho_pid": 502645,
                "ballotpedia": "Fred_Doucette",
                "sponsor_type_id": 2,
                "sponsor_order": 2,
                "committee_sponsor": 0,
                "committee_id": 0,
                "state_federal": 0
            },
            {
                "people_id": 10920,
                "person_hash": "ocox7vyt",
                "party_id": "2",
                "state_id": 29,
                "party": "R",
                "role_id": 1,
                "role": "Rep",
                "name": "Jeanine Notter",
                "first_name": "Jeanine",
                "middle_name": "M.",
                "last_name": "Notter",
                "suffix": "",
                "nickname": "",
                "district": "HD-21-HIL",
                "ftm_eid": 13004224,
                "votesmart_id": 122804,
                "opensecrets_id": "",
                "knowwho_pid": 296536,
                "ballotpedia": "Jeanine_Notter",
                "sponsor_type_id": 2,
                "sponsor_order": 3,
                "committee_sponsor": 0,
                "committee_id": 0,
                "state_federal": 0
            },
            {
                "people_id": 4753,
                "person_hash": "e4zrb1mf",
                "party_id": "2",
                "state_id": 29,
                "party": "R",
                "role_id": 1,
                "role": "Rep",
                "name": "Andrew Renzullo",
                "first_name": "Andrew",
                "middle_name": "",
                "last_name": "Renzullo",
                "suffix": "",
                "nickname": "",
                "district": "HD-37-HIL",
                "ftm_eid": 6665308,
                "votesmart_id": 43000,
                "opensecrets_id": "",
                "knowwho_pid": 228826,
                "ballotpedia": "Andrew_Renzullo",
                "sponsor_type_id": 2,
                "sponsor_order": 4,
                "committee_sponsor": 0,
                "committee_id": 0,
                "state_federal": 0
            }
        ],
        "sasts": [],
        "subjects": [],
        "texts": [
            {
                "doc_id": 2462107,
                "date": "0000-00-00",
                "type": "Introduced",
                "type_id": 1,
                "mime": "text/html",
                "mime_id": 1,
                "url": "https://legiscan.com/NH/text/HB1337/id/2462107",
                "state_link": "https://gencourt.state.nh.us/bill_status/legacy/bs2016/billText.aspx?sy=2022&id=1388&txtFormat=html",
                "text_size": 8059,
                "text_hash": "94fc0d768017be4733523dc75a35c9a1"
            },
            {
                "doc_id": 2551921,
                "date": "2022-03-17",
                "type": "Amended",
                "type_id": 3,
                "mime": "text/html",
                "mime_id": 1,
                "url": "https://legiscan.com/NH/text/HB1337/id/2551921",
                "state_link": "https://gencourt.state.nh.us/bill_status/legacy/bs2016/billText.aspx?sy=2022&txtFormat=html&v=HA&id=1388",
                "text_size": 8116,
                "text_hash": "cc4df320a5eb14cea2c6e6e792e5716a"
            }
        ],
        "votes": [
            {
                "roll_call_id": 1171868,
                "date": "2022-03-17",
                "desc": "OTPA",
                "yea": 179,
                "nay": 153,
                "nv": 28,
                "absent": 30,
                "total": 390,
                "passed": 1,
                "chamber": "H",
                "chamber_id": 67,
                "url": "https://legiscan.com/NH/rollcall/HB1337/id/1171868",
                "state_link": "https://gencourt.state.nh.us/bill_status/legacy/bs2016/Roll_Calls/billstatus_rcdetails.aspx?vs=142&sy=2022&lb=H&eb=HB1337&sortoption=&txtsessionyear=2022&txtbillnumber=HB1337&ddlsponsors=&lsr=2295"
            }
        ],
        "amendments": [],
        "supplements": [],
        "calendar": [
            {
                "type_id": 1,
                "type": "Hearing",
                "date": "2022-02-03",
                "time": "13:00",
                "location": "Legislative Office Building305-307",
                "description": "Labor, Industrial and Rehabilitative Services Public Hearing"
            },
            {
                "type_id": 1,
                "type": "Hearing",
                "date": "2022-03-09",
                "time": "10:00",
                "location": "Legislative Office Building 305-307",
                "description": "Labor, Industrial and Rehabilitative Services Executive Session"
            },
            {
                "type_id": 1,
                "type": "Hearing",
                "date": "2022-03-09",
                "time": "10:00",
                "location": "Legislative Office Building305-307",
                "description": "Labor, Industrial and Rehabilitative Services Executive Session"
            },
            {
                "type_id": 1,
                "type": "Hearing",
                "date": "2022-04-06",
                "time": "10:00",
                "location": "Room 103, State House",
                "description": "Executive Departments and Administration Hearing"
            }
        ],
        "full_text": "new paragraph unemployment compensation weekly benefit amount amend rsa by inserting after paragraph iii the following new paragraph a notwithstanding rsa and the maximum benefit amounts in paragraph i for unemployment compensation claims submitted during a calendar year the duration of benefits under this chapter shall be limited to weeks if the state s average unemployment rate is at or below percent plus one additional week for each percent increment in the state s average unemployment rate above percent up to a maximum of weeks if the state s average unemployment rate exceeds percent b in this paragraph state average unemployment rate shall mean the average of the months for the most recent fourth calendar year quarter of the seasonally adjusted total unemployment rates as determined and benchmarked by the department of labor"
    }
}